{"assets/.env":["assets/.env"],"assets/images/apple.svg":["assets/images/apple.svg"],"assets/images/bottom_nav_bar_home.svg":["assets/images/bottom_nav_bar_home.svg"],"assets/images/bottom_nav_bar_map.svg":["assets/images/bottom_nav_bar_map.svg"],"assets/images/bottom_nav_bar_more.svg":["assets/images/bottom_nav_bar_more.svg"],"assets/images/bottom_nav_bar_pill.svg":["assets/images/bottom_nav_bar_pill.svg"],"assets/images/email.svg":["assets/images/email.svg"],"assets/images/facebook.svg":["assets/images/facebook.svg"],"assets/images/google.svg":["assets/images/google.svg"],"assets/images/instagram.svg":["assets/images/instagram.svg"],"assets/images/logo.png":["assets/images/logo.png"],"assets/images/logo.svg":["assets/images/logo.svg"],"assets/images/logo_text.png":["assets/images/logo_text.png"],"assets/images/logo_text.svg":["assets/images/logo_text.svg"],"assets/images/obscure_icon.svg":["assets/images/obscure_icon.svg"],"assets/images/twitter.svg":["assets/images/twitter.svg"]}